charcoal/__init__.py
charcoal/client.py
charcoal/helpers.py
charcoal/packets.py
charcoal-0.2.0.dist-info/DESCRIPTION.rst
charcoal-0.2.0.dist-info/METADATA
charcoal-0.2.0.dist-info/RECORD
charcoal-0.2.0.dist-info/WHEEL
charcoal-0.2.0.dist-info/metadata.json
charcoal-0.2.0.dist-info/top_level.txt
