Metadata-Version: 2.0
Name: charcoal
Version: 0.2.0
Summary: Opionionated high level StatsD client
Home-page: https://github.com/cknv/charcoal
Author: Esben Sonne
Author-email: esbensonne+code@gmail.com
License: MIT
Platform: UNKNOWN
Classifier: Development Status :: 3 - Alpha
Classifier: Intended Audience :: Developers
Classifier: License :: OSI Approved :: MIT License
Classifier: Programming Language :: Python :: 3.3
Classifier: Programming Language :: Python :: 3.4
Classifier: Programming Language :: Python :: 3.5
